qbo_db_connector/__init__.py
qbo_db_connector/extract.py
qbo_db_connector/extract_ddl.sql
qbo_db_connector/load.py
qbo_db_connector/load_ddl.sql
test/__init__.py
test/common/__init__.py
test/common/utilities.py
test/integration/__init__.py
test/integration/conftest.py
test/integration/test_qbo.py
test/unit/__init__.py
test/unit/conftest.py
test/unit/test_extracts.py
test/unit/test_load.py
test/unit/test_mocks.py
qbo_db_connector-1.1.0.dist-info/LICENSE
qbo_db_connector-1.1.0.dist-info/METADATA
qbo_db_connector-1.1.0.dist-info/WHEEL
qbo_db_connector-1.1.0.dist-info/top_level.txt
qbo_db_connector-1.1.0.dist-info/RECORD
